tramas/CrearTrama.py
tramas/__init__.py
LIBRERIAS-1.0.0.dist-info/LICENSE
LIBRERIAS-1.0.0.dist-info/METADATA
LIBRERIAS-1.0.0.dist-info/WHEEL
LIBRERIAS-1.0.0.dist-info/top_level.txt
LIBRERIAS-1.0.0.dist-info/RECORD
