Metadata-Version: 2.1
Name: LIBRERIAS
Version: 1.0.0
Summary: creacion de funcion para crear tramas
Author: Anthony Arevalo
License: MIT
License-File: LICENSE
